{
  "projectName": "TestProject",
  "ohosSdkPath": "D:\\DevEco Studio\\sdk\\default\\openharmony\\ets",
  "hmsSdkPath": "D:\\DevEco Studio\\sdk\\default\\hms\\ets",
  "projectPath": "D:\\arkProject",
  "product": "default",
  "files": [
    "**/*.ets",
    "**/*.ts"
  ],
  "ignored": [
    "**/AppScope/**/*",
    "**/common/**/*",
    "**/feature/**/*",
    "**/hvigor/**/*",
    "**/product/**/*",
    "**/signature/**/*",
    "**/node_modules/**/*",
    "**/build/**/*"
  ],
  "ignoreFiles": [
    {
      "filePath": "xxx",
      "disableLine": [
        {
          "line": 1,
          "rules": [
            "rule1",
            "rule2"
          ]
        },
        {}
      ]
    },
    {
      "filePath": "abc"
    }
  ],
  "excluded": [
    "**/*.ts"
  ],
  "rules": [
    "@performance/avoid-empty-callback-check:3",
    "@performance/cachemode-check:1",
    "@performance/foreach-args-check:1",
    "@performance/timezone-interface-check:3",
    "@performance/union-type-array-check:3",
    "@performance/sparse-array-check:3",
    "@performance/number-init-check:1",
    "@performance/high-frequency-log-check:3",
    "@performance/start-window-icon-check:3",
    "@performance/waterflow-data-preload-check:3"
  ],
  "ruleSet": [],
  "overrides": []
}